booklisten/__init__.py
booklisten/__main__.py
BookListen-1.0.5.dist-info/METADATA
BookListen-1.0.5.dist-info/WHEEL
BookListen-1.0.5.dist-info/entry_points.txt
BookListen-1.0.5.dist-info/top_level.txt
BookListen-1.0.5.dist-info/RECORD
