Metadata-Version: 2.1
Name: BookListen
Version: 1.0.5
Summary: A command line tool to convert text files to audiobooks
Home-page: https://github.com/mordy-python/booklisten
Author: Israel Waldner
Author-email: imky171@gmail.com
License: UNKNOWN
Platform: any
Classifier: Programming Language :: Python :: 3
Classifier: License :: OSI Approved :: MIT License
Classifier: Operating System :: OS Independent
Requires-Python: >=3.6
Requires-Dist: click
Requires-Dist: gtts
